README
setup.py
ssh_import_id/__init__.py
ssh_import_id/ssh_import_id.py
ssh_import_id.egg-info/PKG-INFO
ssh_import_id.egg-info/SOURCES.txt
ssh_import_id.egg-info/dependency_links.txt
ssh_import_id.egg-info/requires.txt
ssh_import_id.egg-info/top_level.txt
usr/bin/ssh-import-id
usr/bin/ssh-import-id-gh
usr/bin/ssh-import-id-lp