Metadata-Version: 1.0
Name: ssh-import-id
Version: 5.3
Summary: Authorize SSH public keys from trusted online identities
Home-page: https://launchpad.net/ssh-import-id
Author: Dustin Kirkland, Casey Marshall
Author-email: dustin.kirkland@gmail.com, casey.marshall@gmail.com
License: GPLv3
Keywords: ssh public key
Platform: any
